AUTHORS.md
CHANGELOG.md
CONTRIBUTING.md
MANIFEST.in
README.md
_version.py
requirements.txt
setup.py
pyblux/__init__.py
pyblux/blux.py
pyblux/logger.py
pyblux/utils.py
pyblux.egg-info/PKG-INFO
pyblux.egg-info/SOURCES.txt
pyblux.egg-info/dependency_links.txt
pyblux.egg-info/top_level.txt