Metadata-Version: 2.1
Name: pyblux
Version: 0.0.3
Summary: A Powerful suite of fast and intuitive Python ETL utilities
Home-page: https://pypi.org/project/pyblux
Author: Bertin Nono
Author-email: bertin.nono@delta.com
License: MIT
Project-URL: Code, https://github.com/bertin-nono/pyblux
Project-URL: Issue Tracker, https://github.com/bertin-nono/pyblux/issues
Project-URL: Documentation, https://github.com/bertin-nono/pyblux/readme.md
Project-URL: Homepage, https://pypi.org/project/pyblux
Project-URL: Download, https://pypi.org/project/pyblux/
Keywords: etl,database,postgres,aurora,Oracle,Microsoft,Teams
Platform: any
Classifier: Development Status :: 5 - Production/Stable
Classifier: Intended Audience :: Developers
Classifier: Intended Audience :: Information Technology
Classifier: Intended Audience :: Science/Research
Classifier: License :: OSI Approved :: MIT License
Classifier: Natural Language :: English
Classifier: Operating System :: OS Independent
Classifier: Programming Language :: Python :: 3
Classifier: Topic :: Database
Classifier: Topic :: Scientific/Engineering :: GIS
Requires-Python: >= 3.6
